account/__init__.py
account/admin.py
account/fcm/__init__.py
account/fcm/legacy.py
account/fcm/v1.py
account/migrations/0001_initial.py
account/migrations/0003_member_phone_number.py
account/migrations/0004_group_modified_alter_group_created.py
account/migrations/0005_member_auth_code_expires.py
account/migrations/0006_member_security_token.py
account/migrations/0007_authtoken_signature_authsession.py
account/migrations/0008_memberdevice_memberdevicemetadata.py
account/migrations/0009_alter_member_phone_number.py
account/migrations/0010_delete_authtoken.py
account/migrations/0011_authtoken.py
account/migrations/0012_settings_settingsmetadata.py
account/migrations/0013_memberdevice_ip.py
account/migrations/0014_alter_notificationmemberrecord_member.py
account/migrations/0015_memberdevice_buid.py
account/migrations/0016_authsession_buid.py
account/migrations/0017_rename_requires_topt_member_requires_totp.py
account/migrations/0018_userpasskey.py
account/migrations/0019_group_location.py
account/migrations/0020_cloudcredentials_cloudcredentialsmetadata.py
account/migrations/0021_alter_cloudcredentials_group.py
account/migrations/0022_alter_memberdevice_modified.py
account/migrations/0023_authsession_method.py
account/migrations/__init__.py
account/models/__init__.py
account/models/device.py
account/models/feeds.py
account/models/group.py
account/models/legacy.py
account/models/member.py
account/models/membership.py
account/models/notify.py
account/models/passkeys.py
account/models/session.py
account/models/settings.py
account/oauth/__init__.py
account/oauth/google.py
account/passkeys/__init__.py
account/passkeys/core.py
account/periodic.py
account/rpc/__init__.py
account/rpc/auth.py
account/rpc/device.py
account/rpc/group.py
account/rpc/member.py
account/rpc/notify.py
account/rpc/oauth.py
account/rpc/passkeys.py
account/rpc/settings.py
account/settings.py
account/templates/email/base.html
account/templates/email/invite.html
account/templates/email/plain/base.html
django_restit-4.2.182.dist-info/LICENSE.md
django_restit-4.2.182.dist-info/METADATA
django_restit-4.2.182.dist-info/WHEEL
django_restit-4.2.182.dist-info/RECORD
