Metadata-Version: 2.3
Name: django-restit
Version: 4.2.182
Summary: A Rest Framework for DJANGO
License: MIT
Author: Ian Starnes
Author-email: ians@311labs.com
Requires-Python: >=3.8,<4.0
Classifier: License :: OSI Approved :: MIT License
Classifier: Programming Language :: Python :: 3
Classifier: Programming Language :: Python :: 3.8
Classifier: Programming Language :: Python :: 3.9
Classifier: Programming Language :: Python :: 3.10
Classifier: Programming Language :: Python :: 3.11
Classifier: Programming Language :: Python :: 3.12
Classifier: Programming Language :: Python :: 3.13
Requires-Dist: boto3 (>=1.26.160,<2.0.0)
Requires-Dist: django
Requires-Dist: django-redis-cache (>=3.0.1,<4.0.0)
Requires-Dist: django-redis-sessions (>=0.6.2,<0.7.0)
Requires-Dist: fido2
Requires-Dist: gevent (>=23.7.0,<24.0.0)
Requires-Dist: hashids (>=1.3.1,<2.0.0)
Requires-Dist: inlinestyler
Requires-Dist: mistune (>=2.0.4,<3.0.0)
Requires-Dist: phonenumbers
Requires-Dist: pillow
Requires-Dist: psutil
Requires-Dist: pycountry
Requires-Dist: pycryptodome
Requires-Dist: pygments
Requires-Dist: pyjwt
Requires-Dist: pyobjict (>=1.1.6,<2.0.0)
Requires-Dist: pyotp (>=2.8.0,<3.0.0)
Requires-Dist: pypng
Requires-Dist: pyqrcode (>=1.2.1,<2.0.0)
Requires-Dist: python-dateutil (>=2.8.2,<3.0.0)
Requires-Dist: redis (>=3.0.1,<4.0.0)
Requires-Dist: six
Requires-Dist: twilio
Requires-Dist: ujson
Requires-Dist: uwsgi
Requires-Dist: wsaccel
